addrx/__init__.py
addrx/main.py
addrx/core/__init__.py
addrx/core/addrx_core.py
addrx/model/__init__.py
addrx/model/address_model.py
addrx-0.1.2.dist-info/METADATA
addrx-0.1.2.dist-info/WHEEL
addrx-0.1.2.dist-info/top_level.txt
addrx-0.1.2.dist-info/RECORD
