Metadata-Version: 2.4
Name: addrx
Version: 0.1.2
Summary: A Python client for parsing address using Libpostal API service.
Home-page: https://github.com/joydeep-ghatak/AddrX
Author: Joydeep Ghatak
Author-email: joydeep.ghatak007@gmail.com
License: MIT
Classifier: Programming Language :: Python :: 3
Classifier: Operating System :: OS Independent
Requires-Python: >=3.11
Requires-Dist: annotated-types
Requires-Dist: anyio
Requires-Dist: certifi
Requires-Dist: charset-normalizer
Requires-Dist: h11
Requires-Dist: httpcore
Requires-Dist: httpx
Requires-Dist: idna
Requires-Dist: pydantic
Requires-Dist: pydantic_core
Requires-Dist: requests
Requires-Dist: sniffio
Requires-Dist: typing_extensions
Requires-Dist: urllib3
Dynamic: author
Dynamic: author-email
Dynamic: classifier
Dynamic: description
Dynamic: description-content-type
Dynamic: home-page
Dynamic: license
Dynamic: requires-dist
Dynamic: requires-python
Dynamic: summary
